setup.py
pymusic/__init__.py
pymusic/music.py
pymusic/songs.py
pymusic.egg-info/PKG-INFO
pymusic.egg-info/SOURCES.txt
pymusic.egg-info/dependency_links.txt
pymusic.egg-info/not-zip-safe
pymusic.egg-info/top_level.txt