Metadata-Version: 1.0
Name: pymusic
Version: 0.1
Summary: A music player written using only winsound.Beep
Home-page: http://github.com/Squaar/PyMusic
Author: Matt Dumford
Author-email: mdumford99@gmail.com
License: MIT
Platform: UNKNOWN
